pynicehash/__init__.py
pynicehash/mining_status.py
pynicehash/miningdevice.py
pynicehash/miningrig.py
pynicehash/nicehash.py
pynicehash-0.0.13.dist-info/METADATA
pynicehash-0.0.13.dist-info/WHEEL
pynicehash-0.0.13.dist-info/top_level.txt
pynicehash-0.0.13.dist-info/RECORD
