Metadata-Version: 2.1
Name: pynicehash
Version: 0.0.13
Summary: Python to interac with Nicehash API v2
Home-page: https://github.com/nslythe/pynicehash
Author: Nicolas Slythe
Author-email: pynicehash@slythe.net
Project-URL: Bug Tracker, https://github.com/nslythe/pynicehash/issues
Classifier: Programming Language :: Python :: 3
Classifier: License :: OSI Approved :: MIT License
Classifier: Operating System :: OS Independent
Requires-Python: >=3.6
Requires-Dist: requests
